{
  "category": "Chief Engineer Bentley",
  "page": 2,
  "title": "April 19, 2077",
  "sorting_index": 2,
  "body": "Busy day today but got a lot of stuff done. I went over the schedule and assigned roles to my team members. I split the team into three groups. Each group was tasked a few levels to assess. Looks like it is going to take quite a few new parts and elbow grease to make the dam operational again but everyone is optimistic despite rumors of war.",
  "sound": "",
  "commands": {},
  "autoplay": false,
  "notify": false,
  "hidden": false
}